seer/__init__.py
seer/config.py
seer/llm.py
seer/logger.py
seer/agents/README.md
seer/agents/__init__.py
seer/agents/workflow_agent/__init__.py
seer/agents/workflow_agent/agent.py
seer/agents/workflow_agent/context.py
seer/agents/workflow_agent/schema_context.py
seer/agents/workflow_agent/utils.py
seer/agents/workflow_agent/skills/GMAIL.md
seer/agents/workflow_agent/skills/SUPABASE.md
seer/agents/workflow_agent/templates/form_to_gmail_alert.json
seer/agents/workflow_agent/templates/github_pr_to_slack.json
seer/agents/workflow_agent/templates/gmail_to_supabase_log.json
seer/agents/workflow_agent/templates/schedule_daily_report.json
seer/agents/workflow_agent/templates/supabase_to_gmail_welcome.json
seer/agents/workflow_agent/tools/__init__.py
seer/agents/workflow_agent/tools/discovery_tools.py
seer/agents/workflow_agent/tools/workflow_tools.py
seer/analytics/__init__.py
seer/analytics/analytics.py
seer/analytics/workflows.py
seer/api/README.md
seer/api/__init__.py
seer/api/main.py
seer/api/router.py
seer/api/agents/checkpointer.py
seer/api/agents/traces.py
seer/api/agents/workflow/__init__.py
seer/api/agents/workflow/chat_schema.py
seer/api/agents/workflow/chat_services.py
seer/api/agents/workflow/models.py
seer/api/agents/workflow/router.py
seer/api/agents/workflow/services.py
seer/api/core/__init__.py
seer/api/core/errors.py
seer/api/core/middleware/analytics.py
seer/api/core/middleware/auth.py
seer/api/core/middleware/correlation.py
seer/api/core/middleware/path_allowlist.py
seer/api/core/middleware/usage_limit.py
seer/api/forms/__init__.py
seer/api/forms/router.py
seer/api/forms/validation.py
seer/api/integrations/README.md
seer/api/integrations/models.py
seer/api/integrations/resource_router.py
seer/api/integrations/router.py
seer/api/integrations/services.py
seer/api/models/__init__.py
seer/api/models/router.py
seer/api/models/schema.py
seer/api/subscriptions/__init__.py
seer/api/subscriptions/clerk_sync.py
seer/api/subscriptions/middleware.py
seermcp-0.1.4.dist-info/METADATA
seermcp-0.1.4.dist-info/WHEEL
seermcp-0.1.4.dist-info/licenses/LICENSE
seermcp-0.1.4.dist-info/RECORD
