Metadata-Version: 2.4
Name: seermcp
Version: 0.1.4
Summary: Seer - Multi-Agent System for Evaluating AI Agents
Project-URL: Homepage, https://www.getseer.dev
Project-URL: Documentation, https://github.com/seer-engg/seer#readme
Project-URL: Repository, https://github.com/seer-engg/seer
Project-URL: Issues, https://github.com/seer-engg/seer/issues
Author-email: Lokesh Danu <lokesh@getseer.dev>, Akshay Sharma <akshay@getseer.dev>
License-Expression: MIT
License-File: LICENSE
Requires-Python: >=3.12
Requires-Dist: aerich>=0.9.2
Requires-Dist: aiosqlite>=0.20.0
Requires-Dist: asyncpg>=0.31.0
Requires-Dist: authlib>=1.6.6
Requires-Dist: coolname==2.2.0
Requires-Dist: croniter>=2.0.0
Requires-Dist: fastapi>=0.115.0
Requires-Dist: httpx>=0.28.1
Requires-Dist: itsdangerous>=2.1.0
Requires-Dist: jsonschema>=4.25.1
Requires-Dist: langchain-anthropic>=1.0.0
Requires-Dist: langchain-chroma>=0.1.0
Requires-Dist: langchain-mcp-adapters==0.1.12
Requires-Dist: langchain-openai>=1.0.2
Requires-Dist: langchain>=1.1.2
Requires-Dist: langgraph-api==0.5.33
Requires-Dist: langgraph-checkpoint-postgres<4.0.0,>=3.0.1
Requires-Dist: langgraph-checkpoint<4.0.0,>=3.0.1
Requires-Dist: langgraph>=1.0.3
Requires-Dist: posthog>=3.5.0
Requires-Dist: psycopg[binary]>=3.1.0
Requires-Dist: pydantic-settings>=2.0.0
Requires-Dist: pydantic>=2.12.4
Requires-Dist: python-dotenv>=1.0.0
Requires-Dist: pytz>=2024.1
Requires-Dist: pyyaml>=6.0.3
Requires-Dist: requests>=2.32.3
Requires-Dist: restrictedpython>=7.0
Requires-Dist: stripe>=10.0.0
Requires-Dist: taskiq-redis>=1.2.1
Requires-Dist: taskiq>=0.12.1
Requires-Dist: tavily-python>=0.7.12
Requires-Dist: tenacity>=9.1.2
Requires-Dist: tortoise-orm[asyncpg]>=0.25.2
